LICENSE
MANIFEST.in
README.md
pyproject.toml
setup.cfg
setup.py
tap_zuora/__init__.py
tap_zuora/apis.py
tap_zuora/client.py
tap_zuora/discover.py
tap_zuora/exceptions.py
tap_zuora/sync.py
tap_zuora/utils.py
tap_zuora.egg-info/PKG-INFO
tap_zuora.egg-info/SOURCES.txt
tap_zuora.egg-info/dependency_links.txt
tap_zuora.egg-info/entry_points.txt
tap_zuora.egg-info/requires.txt
tap_zuora.egg-info/top_level.txt
tests/test_zuora_all_fields.py
tests/test_zuora_automatic_fields.py
tests/test_zuora_bookmarking.py
tests/test_zuora_discovery.py
tests/test_zuora_interrupted_sync.py
tests/test_zuora_start_date.py