Metadata-Version: 2.1
Name: tap-zuora
Version: 1.5.0
Summary: Singer.io tap for extracting data from the Zuora API
Home-page: https://singer.io
Author: Stitch
Classifier: Programming Language :: Python :: 3 :: Only
License-File: LICENSE
Requires-Dist: singer-python==5.13.0
Requires-Dist: requests==2.32.3
Requires-Dist: pendulum==1.2.0
Requires-Dist: backoff==1.8.0
Provides-Extra: dev
Requires-Dist: ipdb; extra == "dev"
Requires-Dist: pylint; extra == "dev"
